docket/__init__.py
docket/__main__.py
docket/_cancellation.py
docket/_cli_support.py
docket/_docket_snapshot.py
docket/_execution_progress.py
docket/_prometheus_exporter.py
docket/_redis.py
docket/_result_store.py
docket/_telemetry.py
docket/_uuid7.py
docket/agenda.py
docket/annotations.py
docket/cli.py
docket/docket.py
docket/execution.py
docket/instrumentation.py
docket/py.typed
docket/strikelist.py
docket/tasks.py
docket/testing.py
docket/worker.py
docket/dependencies/__init__.py
docket/dependencies/_base.py
docket/dependencies/_concurrency.py
docket/dependencies/_contextual.py
docket/dependencies/_cron.py
docket/dependencies/_functional.py
docket/dependencies/_perpetual.py
docket/dependencies/_progress.py
docket/dependencies/_resolution.py
docket/dependencies/_retry.py
docket/dependencies/_timeout.py
pydocket-0.17.4.dist-info/METADATA
pydocket-0.17.4.dist-info/WHEEL
pydocket-0.17.4.dist-info/entry_points.txt
pydocket-0.17.4.dist-info/licenses/LICENSE
pydocket-0.17.4.dist-info/RECORD
