Metadata-Version: 2.4
Name: pydocket
Version: 0.17.4
Summary: A distributed background task system for Python functions
Project-URL: Homepage, https://github.com/chrisguidry/docket
Project-URL: Bug Tracker, https://github.com/chrisguidry/docket/issues
Author-email: Chris Guidry <guid@omg.lol>
License: # Released under MIT License
License-File: LICENSE
Classifier: Development Status :: 4 - Beta
Classifier: License :: OSI Approved :: MIT License
Classifier: Operating System :: OS Independent
Classifier: Programming Language :: Python :: 3
Classifier: Programming Language :: Python :: 3.10
Classifier: Programming Language :: Python :: 3.11
Classifier: Programming Language :: Python :: 3.12
Classifier: Programming Language :: Python :: 3.13
Classifier: Programming Language :: Python :: 3.14
Classifier: Typing :: Typed
Requires-Python: >=3.10
Requires-Dist: cloudpickle>=3.1.1
Requires-Dist: croniter>=6
Requires-Dist: exceptiongroup>=1.2.0; python_version < '3.11'
Requires-Dist: fakeredis[lua]>=2.32.1
Requires-Dist: opentelemetry-api>=1.33.0
Requires-Dist: prometheus-client>=0.21.1
Requires-Dist: py-key-value-aio[memory,redis]>=0.3.0
Requires-Dist: python-json-logger>=2.0.7
Requires-Dist: redis>=5
Requires-Dist: rich>=13.9.4
Requires-Dist: taskgroup>=0.2.2; python_version < '3.11'
Requires-Dist: typer>=0.15.1
Requires-Dist: typing-extensions>=4.12.0
Provides-Extra: metrics
Requires-Dist: opentelemetry-sdk>=1.33.0; extra == 'metrics'
